nlpsig/__init__.py
nlpsig/classification_utils.py
nlpsig/data_preparation.py
nlpsig/dimensionality_reduction.py
nlpsig/encode_text.py
nlpsig/plot_embedding.py
nlpsig/py.typed
nlpsig/_compat/__init__.py
nlpsig/_compat/typing.py
nlpsig-0.2.2.dist-info/METADATA
nlpsig-0.2.2.dist-info/WHEEL
nlpsig-0.2.2.dist-info/licenses/LICENSE
nlpsig-0.2.2.dist-info/RECORD
